temci/__init__.py
temci/build/__init__.py
temci/build/build_processor.py
temci/build/builder.py
temci/misc/README.md
temci/misc/__init__.py
temci/misc/game.py
temci/report/__init__.py
temci/report/report.py
temci/report/report_processor.py
temci/report/rundata.py
temci/report/stats.py
temci/report/testers.py
temci/report/report_resources/custom-mathjax.js
temci/report/report_resources/custom-mathjax.min.js
temci/report/report_resources/download.sh
temci/report/report_resources/webpack.config.js
temci/report/report_resources/css/bootstrap.min.css
temci/report/report_resources/css/jquery.tocify.css
temci/report/report_resources/css/jquery.ui.all.css
temci/report/report_resources/css/style.css
temci/report/report_resources/js/bootstrap.min.js
temci/report/report_resources/js/custom-mathjax.min.js
temci/report/report_resources/js/jquery-ui-1.9.1.custom.min.js
temci/report/report_resources/js/jquery.min.js
temci/report/report_resources/js/script.js
temci/run/__init__.py
temci/run/cpuset.py
temci/run/run_driver.py
temci/run/run_driver_plugin.py
temci/run/run_processor.py
temci/run/run_worker_pool.py
temci/scripts/__init__.py
temci/scripts/cli.py
temci/scripts/run.py
temci/scripts/temci_completion.py
temci/scripts/version.py
temci/scripts/cpu_cache/disable/Makefile
temci/scripts/cpu_cache/disable/disable_cache.c
temci/scripts/cpu_cache/disable/disable_cache.mod.c
temci/scripts/cpu_cache/flush/Makefile
temci/scripts/cpu_cache/flush/flush_cache.c
temci/scripts/cpu_cache/flush/flush_cache.mod.c
temci/scripts/rusage/Makefile
temci/scripts/rusage/header.c
temci/scripts/rusage/rusage.c
temci/setup/__init__.py
temci/setup/setup.py
temci/utils/__init__.py
temci/utils/click_helper.py
temci/utils/config_utils.py
temci/utils/curses.py
temci/utils/envinfo.py
temci/utils/library_init.py
temci/utils/mail.py
temci/utils/number.py
temci/utils/plugin.py
temci/utils/registry.py
temci/utils/settings.py
temci/utils/sudo_utils.py
temci/utils/typecheck.py
temci/utils/util.py
temci/utils/vcs.py
temci-0.8.5.dist-info/LICENSE
temci-0.8.5.dist-info/METADATA
temci-0.8.5.dist-info/WHEEL
temci-0.8.5.dist-info/entry_points.txt
temci-0.8.5.dist-info/top_level.txt
temci-0.8.5.dist-info/RECORD
