Metadata-Version: 2.1
Name: temci
Version: 0.8.5
Summary: Advanced benchmarking tool
Home-page: https://github.com/parttimenerd/temci
Author: Johannes Bechberger
Author-email: me@mostlynerdless.de
License: GPLv3
Platform: linux
Classifier: Programming Language :: Python :: 3.6
Classifier: Programming Language :: Python :: 3.7
Classifier: Programming Language :: Python :: 3.8
Classifier: Programming Language :: Python :: 3 :: Only
Classifier: Operating System :: POSIX :: Linux
Classifier: Topic :: System :: Benchmark
Classifier: License :: OSI Approved :: GNU General Public License v3 or later (GPLv3+)
Classifier: Development Status :: 4 - Beta
Classifier: Environment :: Console
Classifier: Intended Audience :: Developers
Requires-Dist: click
Requires-Dist: cpuset-py3
Requires-Dist: fn
Requires-Dist: humanfriendly
Requires-Dist: matplotlib
Requires-Dist: psutil
Requires-Dist: pytimeparse
Requires-Dist: pyyaml
Requires-Dist: rainbow-logging-handler
Requires-Dist: seaborn
Requires-Dist: tablib
Requires-Dist: wcwidth
